{
  "api": "https://api.shopbase.com",
  "username": "havu@beeketing.net",
  "password": "qafront@123",
  "shop_name": "sbase-new",
  "cases": {
    "TC_API_SINGLE_02": {
      "data": {
        "url": "https://sbase-new.onshopbase.com/api/bootstrap/next.json",
        "request": {},
        "response": {
          "status": 200,
          "data": {
            "success": true
          }
        }
      }
    },
    "TC_API_SINGLE_01": {
      "data": {
        "url": "https://sbase-new.onshopbase.com/api/bootstrap/next.json",
        "request": {},
        "response": {
          "status": 200,
          "data": {
            "success": true
          }
        }
      }
    }
  }
}
